redesign/info/__init__.py
redesign-2021.7.dist-info/LICENSE
redesign-2021.7.dist-info/METADATA
redesign-2021.7.dist-info/WHEEL
redesign-2021.7.dist-info/top_level.txt
redesign-2021.7.dist-info/RECORD
