Metadata-Version: 2.1
Name: redesign
Version: 2021.7
Summary: Namespace for Redesigning Psychiatry packages
Home-page: https://github.com/redesigningpsychiatry
Author: Sander Voerman
Author-email: sander@redesigningpsychiatry.org
License: UNKNOWN
Platform: UNKNOWN
Classifier: Programming Language :: Python :: 3
Classifier: Topic :: Documentation
Classifier: Operating System :: OS Independent
Requires-Python: >=3.6
License-File: LICENSE
